monitoring_system_sdk/__init__.py
monitoring_system_sdk/main.py
monitoring_system_sdk/mixins.py
monitoring_system_sdk/tests/__init__.py
monitoring_system_sdk/tests/main_tests.py
qodex_ms_sdk-1.2.2.dist-info/LICENSE
qodex_ms_sdk-1.2.2.dist-info/METADATA
qodex_ms_sdk-1.2.2.dist-info/WHEEL
qodex_ms_sdk-1.2.2.dist-info/top_level.txt
qodex_ms_sdk-1.2.2.dist-info/RECORD
