Metadata-Version: 2.1
Name: qodex-ms-sdk
Version: 1.2.2
Author: PunchyArchy
License-File: LICENSE
Requires-Dist: requests
